text2emoji/__init__.py
text2emoji/converter.py
text2emoji-0.1.1.dist-info/METADATA
text2emoji-0.1.1.dist-info/WHEEL
text2emoji-0.1.1.dist-info/top_level.txt
text2emoji-0.1.1.dist-info/RECORD
